exportroi.py
imgprofiler.py
importpw.py
importroi.py
napari_jroireader.py
napari_jroiwriter.py
writepw.py
napari_jroitools-0.0.19.dist-info/METADATA
napari_jroitools-0.0.19.dist-info/WHEEL
napari_jroitools-0.0.19.dist-info/entry_points.txt
napari_jroitools-0.0.19.dist-info/license.txt
napari_jroitools-0.0.19.dist-info/top_level.txt
napari_jroitools-0.0.19.dist-info/RECORD
