Metadata-Version: 2.1
Name: napari-jroitools
Version: 0.0.19
Summary: A plugin to read and write ImageJ roi files into a napari shapes or points layer.
Home-page: https://github.com/jayunruh/napari_jroitools
Author: Jay Unruh
License: GNU GPLv2
Platform: UNKNOWN
Requires-Python: >=3.6
License-File: license.txt
Requires-Dist: napari-plugin-engine (>=0.1.4)
Requires-Dist: numpy
Requires-Dist: numba
